alibuild-1.17.35.data/scripts/aliBuild
alibuild-1.17.35.data/scripts/aliDeps
alibuild-1.17.35.data/scripts/aliDoctor
alibuild-1.17.35.data/scripts/alienv
alibuild-1.17.35.data/scripts/pb
alibuild-1.17.35.dist-info/licenses/LICENSE.md
alibuild_helpers/__init__.py
alibuild_helpers/_version.py
alibuild_helpers/analytics.py
alibuild_helpers/args.py
alibuild_helpers/build.py
alibuild_helpers/build_template.sh
alibuild_helpers/clean.py
alibuild_helpers/cmd.py
alibuild_helpers/deps.py
alibuild_helpers/doctor.py
alibuild_helpers/git.py
alibuild_helpers/init.py
alibuild_helpers/log.py
alibuild_helpers/scm.py
alibuild_helpers/sl.py
alibuild_helpers/sync.py
alibuild_helpers/templating_plugin.py
alibuild_helpers/utilities.py
alibuild_helpers/workarea.py
debian/changelog
debian/compat
debian/control
debian/copyright
debian/files
debian/rules
docs/SUPPORT
docs/mkdocs.yml
docs/docs/alice_logo.png
docs/docs/deps.png
docs/docs/index.md
docs/docs/quick.md
docs/docs/reference.md
docs/docs/troubleshooting.md
docs/docs/user.md
docs/docs/stylesheets/extra.css
templates/alibuild_to_please.jnj
tests/test_analytics.py
tests/test_args.py
tests/test_build.py
tests/test_clean.py
tests/test_cmd.py
tests/test_deps.py
tests/test_doctor.py
tests/test_git.py
tests/test_hashing.py
tests/test_init.py
tests/test_log.py
tests/test_packagelist.py
tests/test_parseRecipe.py
tests/test_sync.py
tests/test_utilities.py
tests/test_workarea.py
tests/testdist/broken1.sh
tests/testdist/broken2.sh
tests/testdist/broken3.sh
tests/testdist/broken4.sh
tests/testdist/broken5.sh
tests/testdist/broken6.sh
tests/testdist/broken7.sh
tests/testdist/clobber-initdotsh.sh
tests/testdist/defaults-o2.sh
tests/testdist/delete-etc.sh
tests/testdist/tracking-env.sh
alibuild-1.17.35.dist-info/METADATA
alibuild-1.17.35.dist-info/WHEEL
alibuild-1.17.35.dist-info/top_level.txt
alibuild-1.17.35.dist-info/RECORD
