Metadata-Version: 2.4
Name: alibuild
Version: 1.17.35
Summary: ALICE Build Tool
Home-page: https://alisw.github.io/alibuild
Author: Giulio Eulisse
Author-email: Giulio Eulisse <giulio.eulisse@cern.ch>, Timo Wilken <timo.wilken@cern.ch>, Sergio Garcia <sergio.garcia@cern.ch>
Project-URL: homepage, https://alisw.github.io/alibuild
Keywords: HEP,ALICE
Classifier: Development Status :: 5 - Production/Stable
Classifier: Intended Audience :: Developers
Classifier: Topic :: Software Development :: Build Tools
Requires-Python: >=3.6
License-File: LICENSE.md
Requires-Dist: pyyaml
Requires-Dist: requests
Requires-Dist: distro
Requires-Dist: jinja2
Requires-Dist: boto3<1.36.0
Provides-Extra: test
Requires-Dist: tox; extra == "test"
Provides-Extra: docs
Requires-Dist: mkdocs; extra == "docs"
Requires-Dist: mkdocs-material; extra == "docs"
Requires-Dist: mkdocs-redirects; extra == "docs"
Dynamic: author
Dynamic: home-page
Dynamic: license-file
